Darko/__init__.py
Darko/base.py
Darko/config.py
Darko/darko.py
Darko/decorators.py
Darko/edge.py
Darko/node.py
Darko/run.py
Darko/serializers.py
Darko/signal_handlers.py
Darko/starter.py
Darko-0.1.data/scripts/run.py
Darko-0.1.dist-info/LICENSE
Darko-0.1.dist-info/METADATA
Darko-0.1.dist-info/WHEEL
Darko-0.1.dist-info/top_level.txt
Darko-0.1.dist-info/RECORD
