Metadata-Version: 2.1
Name: Darko
Version: 0.1
Summary: Darko is lightweight Graph Key-Value store
Home-page: https://github.com/UtkucanBykl/Darko
Author: Utkucan Bıyıklı
Author-email: utkucanbykl@gmail.com
License: UNKNOWN
Platform: UNKNOWN
Classifier: Programming Language :: Python :: 3.7
Classifier: License :: OSI Approved :: MIT License
Classifier: Operating System :: OS Independent
